qualis_zotero/__init__.py
qualis_zotero/__main__.py
qualis_zotero/config.py
qualis_zotero/core.py
qualis_zotero/openalex.py
qualis_zotero/qualis.py
qualis_zotero/zotero.py
qualis_zotero-0.1.5.dist-info/licenses/LICENSE
qualis_zotero-0.1.5.dist-info/METADATA
qualis_zotero-0.1.5.dist-info/WHEEL
qualis_zotero-0.1.5.dist-info/top_level.txt
qualis_zotero-0.1.5.dist-info/RECORD
