Metadata-Version: 2.4
Name: qualis-zotero
Version: 0.1.5
Summary: Integra Zotero, OpenAlex e Qualis CAPES
Author-email: Wilson Vanucci <wilsonvanuccicl@gmail.com>
License: MIT
Project-URL: Homepage, https://github.com/wvanucci/Qualis-Zotero
Project-URL: Documentation, https://qualis-zotero.readthedocs.io
License-File: LICENSE
Requires-Dist: pandas
Requires-Dist: requests
Requires-Dist: PyYAML
Requires-Dist: tqdm
Requires-Dist: thefuzz
Dynamic: license-file
